fastapi_lambda_router/__init__.py
fastapi_lambda_router/router.py
fastapi_lambda_router-0.0.1.dist-info/LICENSE
fastapi_lambda_router-0.0.1.dist-info/METADATA
fastapi_lambda_router-0.0.1.dist-info/WHEEL
fastapi_lambda_router-0.0.1.dist-info/top_level.txt
fastapi_lambda_router-0.0.1.dist-info/RECORD
