Metadata-Version: 2.1
Name: fastapi-lambda-router
Version: 0.0.1
Summary: A fastapi router for AWS Lambda that fixes a small issue
Author-email: Aaron Visschedijk <aaron.visschedijk@gmail.com>
Project-URL: Homepage, https://github.com/aaron-visschedijk/lambda-fastapi-router
Project-URL: Bug Tracker, https://github.com/aaron-visschedijk/lambda-fastapi-router/issues
Classifier: Programming Language :: Python :: 3
Classifier: License :: OSI Approved :: MIT License
Classifier: Operating System :: OS Independent
Requires-Python: >=3.7
License-File: LICENSE
